smartbets_API/__init__.py
smartbets_API/__main__.py
smartbets_API/bet_analyzer.py
smartbets_API/bet_at_rest_api_level.py
smartbets_API/bet_common.py
smartbets_API/configuration_handler.py
smartbets_API/figure_harvester.py
smartbets_API/googler.py
smartbets_API/html_fetcher.py
smartbets_API/interface.py
smartbets_API/predictor.py
smartbets_API/proxyh.py
smartbets_API/tertiary_bet.py
smartbetsAPI-1.3.2.dist-info/LICENSE
smartbetsAPI-1.3.2.dist-info/METADATA
smartbetsAPI-1.3.2.dist-info/WHEEL
smartbetsAPI-1.3.2.dist-info/entry_points.txt
smartbetsAPI-1.3.2.dist-info/top_level.txt
smartbetsAPI-1.3.2.dist-info/RECORD
