Metadata-Version: 2.1
Name: smartbetsAPI
Version: 1.3.2
Summary: Simple football prediction API
Home-page: https://github.com/Simatwa/smartbetsAPI
Author: Smartwa Caleb
Author-email: smartwacaleb@gmail.com
Maintainer: Smartwa Caleb
Maintainer-email: smartwacaleb@gmail.com
License: GPL-3.0
Project-URL: Bug Report, https://github.com/Simatwa/smartbetsAPI/issues/new
Project-URL: Homepage, https://github.com/Simatwa/smartbetsAPI
Project-URL: Source Code, https://github.com/Simatwa/smartbetsAPI
Project-URL: Issue Tracker, https://github.com/Simatwa/smartbetsAPI/issues
Project-URL: Download, https://github.com/Simatwa/smartbetsAPI/releases
Project-URL: Documentation, https://github.com/Simatwa/smartbetsAPI/blob/main/README.md
Keywords: Football,Predictions,Betting API,Soccer predictions,Football Predictions
Classifier: Development Status :: 5 - Production/Stable
Classifier: Environment :: Console
Classifier: Intended Audience :: Developers
Classifier: Intended Audience :: Customer Service
Classifier: Intended Audience :: Other Audience
Classifier: License :: OSI Approved :: GNU General Public License v3 (GPLv3)
Classifier: Operating System :: OS Independent
Classifier: Programming Language :: Python
Classifier: Programming Language :: Python :: 3 :: Only
Classifier: Programming Language :: Python :: 3.9
Classifier: Programming Language :: Python :: 3.10
Classifier: Programming Language :: Python :: 3.11
Classifier: Programming Language :: Python :: 3.12
Classifier: Natural Language :: English
Classifier: Topic :: Software Development :: Libraries :: Python Modules
Classifier: Topic :: Games/Entertainment
Requires-Python: >=3.9
License-File: LICENSE
Requires-Dist: appdirs ==1.4.4
Requires-Dist: requests[socks] ==2.31.0
Requires-Dist: colorama ==0.4.6
Requires-Dist: bs4 ==0.0.1
Requires-Dist: Faker ==15.3.4
Requires-Dist: pyfreeproxies ==0.1.1
Provides-Extra: api
Requires-Dist: fastapi[all] ==0.110.1 ; extra == 'api'
